matchcaselib.py
matchcaselib-0.0.1b0.dist-info/METADATA
matchcaselib-0.0.1b0.dist-info/WHEEL
matchcaselib-0.0.1b0.dist-info/top_level.txt
matchcaselib-0.0.1b0.dist-info/RECORD
