Metadata-Version: 2.1
Name: matchcaselib
Version: 0.0.1b0
Summary: Easy implementation of Python 3.10's structural pattern matching.
Home-page: https://github.com/MasterCoder21/matchcaselib
Author: minecraftpr03
License: UNKNOWN
Platform: UNKNOWN
Classifier: Programming Language :: Python :: 3
Classifier: Programming Language :: Python :: 3.6
Classifier: Programming Language :: Python :: 3.7
Classifier: Programming Language :: Python :: 3.8
Classifier: Programming Language :: Python :: 3.9
Classifier: License :: OSI Approved :: MIT License
Classifier: Operating System :: OS Independent
